LICENSE.md
MANIFEST.in
README.rst
pyproject.toml
requirements.core.txt
requirements.txt
setup.py
core_oaipmh_common_app/__init__.py
core_oaipmh_common_app.egg-info/PKG-INFO
core_oaipmh_common_app.egg-info/SOURCES.txt
core_oaipmh_common_app.egg-info/dependency_links.txt
core_oaipmh_common_app.egg-info/requires.txt
core_oaipmh_common_app.egg-info/top_level.txt
core_oaipmh_common_app/commons/__init__.py
core_oaipmh_common_app/commons/exceptions.py
core_oaipmh_common_app/commons/messages.py
core_oaipmh_common_app/components/__init__.py
core_oaipmh_common_app/components/oai_metadata_format/__init__.py
core_oaipmh_common_app/components/oai_metadata_format/api.py
core_oaipmh_common_app/components/oai_metadata_format/models.py
core_oaipmh_common_app/components/oai_set/__init__.py
core_oaipmh_common_app/components/oai_set/api.py
core_oaipmh_common_app/components/oai_set/models.py
core_oaipmh_common_app/migrations/__init__.py
tests/__init__.py
tests/test_settings.py
tests/components/__init__.py
tests/components/oai_metadata_format/__init__.py
tests/components/oai_metadata_format/tests_unit.py
tests/components/oai_set/__init__.py
tests/components/oai_set/tests/__init__.py
tests/components/oai_set/tests/tests_unit.py